.gitignore
LICENSE
MANIFEST.in
README.rst
requirements.txt
setup.py
lanscan/lanscan.py
lanscan/logging.yaml
lanscan.egg-info/PKG-INFO
lanscan.egg-info/SOURCES.txt
lanscan.egg-info/dependency_links.txt
lanscan.egg-info/entry_points.txt
lanscan.egg-info/requires.txt
lanscan.egg-info/top_level.txt