Metadata-Version: 1.1
Name: lanscan
Version: 0.9.4
Summary: Python 3 module to collect and display information about the hosts and devices on the local network
Home-page: https://github.com/sumpfgottheit/lanscan
Author: Florian Sachs
Author-email: florian.sachs@gmx.at
License: MIT
Keywords: network scanner active passive dpkt html
Platform: UNKNOWN
Classifier: Development Status :: 4 - Beta
Classifier: License :: OSI Approved :: MIT License
Classifier: Programming Language :: Python :: 3.5
Classifier: Operating System :: Unix
Classifier: Topic :: Utilities
Classifier: Environment :: Console
